{"data":{"site":{"siteMetadata":{"title":"Net64 - Super Mario 64 Online","description":"Official website for Net64, a Super Mario 64 mod for playing online.","author":{"name":"Mario Reder","url":"https://github.com/Tarnadas"}}},"markdownRemark":{"html":"<p><a href=\"https://discord.gg/net64\"><img src=\"https://discordapp.com/api/guilds/354358899328942081/widget.png\" alt=\"Discord\"></a>\n<a href=\"https://travis-ci.org/Tarnadas/net64plus\"><img src=\"https://api.travis-ci.org/Tarnadas/net64plus.svg?branch=master\" alt=\"Build Status\"></a></p>\n<p>Net64 aka SM64O allows playing Super Mario 64 in an online multiplayer mode.\nNet64+ is the official continuation of the program and features an integrated server list.</p>\n<p>This repository includes the client software. If you want to host your own dedicated server, please visit the <a href=\"https://github.com/Tarnadas/net64plus-server\">server repository</a>.</p>\n<h2>Download</h2>\n<p>Download the client/server/emulator bundle in the <a href=\"https://github.com/Tarnadas/net64plus/releases\">release section</a>.</p>\n<h2>Server List</h2>\n<p>There is a <a href=\"https://smmdb.ddns.net/net64\">public server list</a> of all Net64+ server, that have enabled listing.</p>","excerpt":"\n Net64 aka SM64O allows playing Super Mario 64 in an online multiplayer mode.\nNet64+ is the official continuation of the program and…","frontmatter":{"title":"Net64+ Client"}}},"pageContext":{"slug":"/net64plus/"}}